StripeSankey/__init__.py
StripeSankey/widget.py
stripesankey-0.3.0.dist-info/METADATA
stripesankey-0.3.0.dist-info/WHEEL
stripesankey-0.3.0.dist-info/licenses/LICENSE
stripesankey-0.3.0.dist-info/RECORD
