Metadata-Version: 2.4
Name: StripeSankey
Version: 0.3.0
Summary: Interactive Sankey diagram widget for topic modeling analysis with sample flow tracing
Project-URL: Homepage, https://github.com/Peiyangg/StripeSankey
Project-URL: Documentation, https://github.com/Peiyangg/StripeSankey#readme
Project-URL: Repository, https://github.com/Peiyangg/StripeSankey.git
Project-URL: Bug Tracker, https://github.com/Peiyangg/StripeSankey/issues
Author-email: Peiyang Huo <peiyang.huo@kuleuven.be>
Maintainer-email: Peiyang Huo <peiyang.huo@kuleuven.be>
License: MIT License
License-File: LICENSE
Keywords: anywidget,interactive,jupyter,microbiome,sankey,topic-modeling,visualization,widget
Classifier: Development Status :: 4 - Beta
Classifier: Framework :: Jupyter
Classifier: Framework :: Jupyter :: JupyterLab
Classifier: Framework :: Jupyter :: JupyterLab :: 3
Classifier: Framework :: Jupyter :: JupyterLab :: 4
Classifier: Intended Audience :: Developers
Classifier: Intended Audience :: Science/Research
Classifier: License :: OSI Approved :: MIT License
Classifier: Programming Language :: Python :: 3
Classifier: Programming Language :: Python :: 3.8
Classifier: Programming Language :: Python :: 3.9
Classifier: Programming Language :: Python :: 3.10
Classifier: Programming Language :: Python :: 3.11
Classifier: Programming Language :: Python :: 3.12
Classifier: Topic :: Scientific/Engineering :: Visualization
Requires-Python: >=3.8
Requires-Dist: anywidget>=0.9.0
Requires-Dist: traitlets>=5.0.0
Provides-Extra: dev
Requires-Dist: black; extra == 'dev'
Requires-Dist: mypy; extra == 'dev'
Requires-Dist: pytest-cov; extra == 'dev'
Requires-Dist: pytest>=6.0; extra == 'dev'
Requires-Dist: ruff; extra == 'dev'
Provides-Extra: docs
Requires-Dist: sphinx; extra == 'docs'
Requires-Dist: sphinx-rtd-theme; extra == 'docs'
